uglad/__init__.py
uglad/main.py
uglad/glad/__init__.py
uglad/glad/glad.py
uglad/glad/glad_params.py
uglad/glad/torch_sqrtm.py
uglad/utils/__init__.py
uglad/utils/metrics.py
uglad/utils/prepare_data.py
uglad-2.0.0.dist-info/METADATA
uglad-2.0.0.dist-info/WHEEL
uglad-2.0.0.dist-info/licenses/LICENSE
uglad-2.0.0.dist-info/RECORD
