Metadata-Version: 2.4
Name: uglad
Version: 2.0.0
Summary: A deep unrolled architecture to recover conditional independence graphs. A better alternative to BCD and other graphical lasso solvers.
Project-URL: Homepage, https://github.com/Harshs27/uglad
Project-URL: Bug Tracker, https://github.com/Harshs27/uglad/issues
Project-URL: Paper, https://arxiv.org/abs/2205.11610
Author-email: Harsh Shrivastava <harshshrivastava111@gmail.com>
License: uGLAD Non-Commercial License  
License-File: LICENSE
Classifier: Programming Language :: Python :: 3
Requires-Python: >=3.13
Requires-Dist: matplotlib
Requires-Dist: networkx
Requires-Dist: numpy
Requires-Dist: pandas
Requires-Dist: pyvis
Requires-Dist: scikit-learn
Requires-Dist: scipy
Requires-Dist: torch
Requires-Dist: torchvision
Provides-Extra: dev
Requires-Dist: ipykernel; extra == 'dev'
Requires-Dist: notebook; extra == 'dev'
